gurunudi/__init__.py
gurunudi/ai.py
gurunudi/config.py
gurunudi/constants.py
gurunudi/lang.py
gurunudi-2.0.3.dist-info/LICENSE
gurunudi-2.0.3.dist-info/METADATA
gurunudi-2.0.3.dist-info/WHEEL
gurunudi-2.0.3.dist-info/top_level.txt
gurunudi-2.0.3.dist-info/RECORD
