Metadata-Version: 2.1
Name: gurunudi
Version: 2.0.3
Summary: The official Python client for Gurunudi AI API
Home-page: http://github.com/guruyuga/gurunudi
Author: GuruYuga
Author-email: contact@gurunudi.com
License: Apache-2.0
Keywords: guruyuga,gurunudi,artificial-intelligence,chatbot,nlp,nlg,nli,machine-learning,sentiment-analysis,natural-language-processing,natural-language-generation,natural-language-inference,machine-translation,autocomplete,autocorrect,spell-check,coreference-resolution,knowledge-graph,expert-system,context-qa,topic-modeling
Platform: UNKNOWN
Classifier: Development Status :: 4 - Beta
Classifier: Environment :: Console
Classifier: Intended Audience :: Developers
Classifier: Intended Audience :: Science/Research
Classifier: License :: OSI Approved :: MIT License
Classifier: Operating System :: POSIX :: Linux
Classifier: Operating System :: MacOS :: MacOS X
Classifier: Operating System :: Microsoft :: Windows
Classifier: Programming Language :: Python :: 2
Classifier: Programming Language :: Python :: 2.7
Classifier: Programming Language :: Python :: 3
Classifier: Programming Language :: Python :: 3.4
Classifier: Programming Language :: Python :: 3.5
Classifier: Programming Language :: Python :: 3.6
Classifier: Topic :: Scientific/Engineering :: Artificial Intelligence
Requires-Dist: requests (>=2.13.0)
